package cn.apppark.mcd.util.file;

import android.content.Context;
import android.content.res.AssetManager;
import android.content.res.Resources;
import android.os.Environment;
import java.io.BufferedReader;
import java.io.File;
import java.io.FileInputStream;
import java.io.InputStreamReader;
import java.io.PrintStream;
import org.apache.http.util.EncodingUtils;

public class SDFileUtils
{
  private String SDCardRoot = Environment.getExternalStorageDirectory().getAbsolutePath() + "/";
  
  public static void clearFoldeFile(String paramString)
  {
    paramString = new File(paramString);
    if ((paramString.exists()) && (paramString.isDirectory()))
    {
      paramString = paramString.listFiles();
      if ((paramString != null) && (paramString.length > 0))
      {
        int i = 0;
        while (i < paramString.length)
        {
          paramString[i].delete();
          i += 1;
        }
      }
    }
  }
  
  /* Error */
  public static void downloadToSd(String paramString, File paramFile)
  {
    // Byte code:
    //   0: aconst_null
    //   1: astore 4
    //   3: aconst_null
    //   4: astore_3
    //   5: aload_0
    //   6: aload_0
    //   7: ldc 31
    //   9: invokevirtual 67	java/lang/String:lastIndexOf	(Ljava/lang/String;)I
    //   12: iconst_1
    //   13: iadd
    //   14: invokevirtual 71	java/lang/String:substring	(I)Ljava/lang/String;
    //   17: astore 5
    //   19: new 21	java/io/File
    //   22: dup
    //   23: aload_1
    //   24: aload 5
    //   26: ldc 73
    //   28: invokestatic 79	java/net/URLDecoder:decode	(Ljava/lang/String;Ljava/lang/String;)Ljava/lang/String;
    //   31: invokespecial 82	java/io/File:<init>	(Ljava/io/File;Ljava/lang/String;)V
    //   34: astore_1
    //   35: aload_1
    //   36: invokevirtual 45	java/io/File:exists	()Z
    //   39: ifeq +14 -> 53
    //   42: aload 5
    //   44: ldc 84
    //   46: invokevirtual 88	java/lang/String:endsWith	(Ljava/lang/String;)Z
    //   49: ifne +4 -> 53
    //   52: return
    //   53: aload_1
    //   54: invokevirtual 91	java/io/File:getParentFile	()Ljava/io/File;
    //   57: astore 5
    //   59: aload 5
    //   61: invokevirtual 45	java/io/File:exists	()Z
    //   64: ifne +9 -> 73
    //   67: aload 5
    //   69: invokevirtual 94	java/io/File:mkdirs	()Z
    //   72: pop
    //   73: new 96	java/net/URL
    //   76: dup
    //   77: aload_0
    //   78: invokespecial 97	java/net/URL:<init>	(Ljava/lang/String;)V
    //   81: invokevirtual 101	java/net/URL:openConnection	()Ljava/net/URLConnection;
    //   84: astore_0
    //   85: aload_0
    //   86: invokevirtual 106	java/net/URLConnection:connect	()V
    //   89: aload_0
    //   90: invokevirtual 110	java/net/URLConnection:getInputStream	()Ljava/io/InputStream;
    //   93: astore_0
    //   94: new 112	java/io/FileOutputStream
    //   97: dup
    //   98: aload_1
    //   99: invokespecial 115	java/io/FileOutputStream:<init>	(Ljava/io/File;)V
    //   102: astore_1
    //   103: sipush 4096
    //   106: newarray <illegal type>
    //   108: astore_3
    //   109: aload_0
    //   110: aload_3
    //   111: invokevirtual 121	java/io/InputStream:read	([B)I
    //   114: istore_2
    //   115: iload_2
    //   116: iconst_m1
    //   117: if_icmpeq +47 -> 164
    //   120: aload_1
    //   121: aload_3
    //   122: iconst_0
    //   123: iload_2
    //   124: invokevirtual 125	java/io/FileOutputStream:write	([BII)V
    //   127: goto -18 -> 109
    //   130: astore 4
    //   132: aload_1
    //   133: astore_3
    //   134: aload 4
    //   136: astore_1
    //   137: aload_1
    //   138: invokevirtual 128	java/io/IOException:printStackTrace	()V
    //   141: aload_0
    //   142: ifnull +7 -> 149
    //   145: aload_0
    //   146: invokevirtual 131	java/io/InputStream:close	()V
    //   149: aload_3
    //   150: ifnull +132 -> 282
    //   153: aload_3
    //   154: invokevirtual 132	java/io/FileOutputStream:close	()V
    //   157: return
    //   158: astore_0
    //   159: aload_0
    //   160: invokevirtual 133	java/lang/Exception:printStackTrace	()V
    //   163: return
    //   164: aload_1
    //   165: invokevirtual 136	java/io/FileOutputStream:flush	()V
    //   168: aload_1
    //   169: invokevirtual 132	java/io/FileOutputStream:close	()V
    //   172: aload_0
    //   173: invokevirtual 131	java/io/InputStream:close	()V
    //   176: aload_0
    //   177: ifnull +7 -> 184
    //   180: aload_0
    //   181: invokevirtual 131	java/io/InputStream:close	()V
    //   184: aload_1
    //   185: invokevirtual 132	java/io/FileOutputStream:close	()V
    //   188: return
    //   189: astore_0
    //   190: aload_0
    //   191: invokevirtual 133	java/lang/Exception:printStackTrace	()V
    //   194: return
    //   195: astore_0
    //   196: aload_0
    //   197: invokevirtual 133	java/lang/Exception:printStackTrace	()V
    //   200: goto -16 -> 184
    //   203: astore_0
    //   204: aload_0
    //   205: invokevirtual 133	java/lang/Exception:printStackTrace	()V
    //   208: goto -59 -> 149
    //   211: astore_1
    //   212: aconst_null
    //   213: astore_0
    //   214: aload 4
    //   216: astore_3
    //   217: aload_0
    //   218: ifnull +7 -> 225
    //   221: aload_0
    //   222: invokevirtual 131	java/io/InputStream:close	()V
    //   225: aload_3
    //   226: ifnull +7 -> 233
    //   229: aload_3
    //   230: invokevirtual 132	java/io/FileOutputStream:close	()V
    //   233: aload_1
    //   234: athrow
    //   235: astore_0
    //   236: aload_0
    //   237: invokevirtual 133	java/lang/Exception:printStackTrace	()V
    //   240: goto -15 -> 225
    //   243: astore_0
    //   244: aload_0
    //   245: invokevirtual 133	java/lang/Exception:printStackTrace	()V
    //   248: goto -15 -> 233
    //   251: astore_1
    //   252: aload 4
    //   254: astore_3
    //   255: goto -38 -> 217
    //   258: astore 4
    //   260: aload_1
    //   261: astore_3
    //   262: aload 4
    //   264: astore_1
    //   265: goto -48 -> 217
    //   268: astore_1
    //   269: goto -52 -> 217
    //   272: astore_1
    //   273: aconst_null
    //   274: astore_0
    //   275: goto -138 -> 137
    //   278: astore_1
    //   279: goto -142 -> 137
    //   282: return
    // Local variable table:
    //   start	length	slot	name	signature
    //   0	283	0	paramString	String
    //   0	283	1	paramFile	File
    //   114	10	2	i	int
    //   4	258	3	localObject1	Object
    //   1	1	4	localObject2	Object
    //   130	123	4	localIOException	java.io.IOException
    //   258	5	4	localObject3	Object
    //   17	51	5	localObject4	Object
    // Exception table:
    //   from	to	target	type
    //   103	109	130	java/io/IOException
    //   109	115	130	java/io/IOException
    //   120	127	130	java/io/IOException
    //   164	176	130	java/io/IOException
    //   153	157	158	java/lang/Exception
    //   184	188	189	java/lang/Exception
    //   180	184	195	java/lang/Exception
    //   145	149	203	java/lang/Exception
    //   5	52	211	finally
    //   53	73	211	finally
    //   73	94	211	finally
    //   221	225	235	java/lang/Exception
    //   229	233	243	java/lang/Exception
    //   94	103	251	finally
    //   103	109	258	finally
    //   109	115	258	finally
    //   120	127	258	finally
    //   164	176	258	finally
    //   137	141	268	finally
    //   5	52	272	java/io/IOException
    //   53	73	272	java/io/IOException
    //   73	94	272	java/io/IOException
    //   94	103	278	java/io/IOException
  }
  
  public static String getFromAssets(String paramString, Context paramContext)
  {
    String str = "";
    try
    {
      BufferedReader localBufferedReader = new BufferedReader(new InputStreamReader(paramContext.getResources().getAssets().open(paramString)));
      for (paramString = str;; paramString = paramString + str)
      {
        str = localBufferedReader.readLine();
        paramContext = paramString;
        if (str == null) {
          break;
        }
      }
      return paramContext;
    }
    catch (Exception paramString)
    {
      paramContext = null;
      paramString.printStackTrace();
    }
  }
  
  /* Error */
  public static android.graphics.drawable.Drawable getImageFromAssetsFile(String paramString, Context paramContext)
  {
    // Byte code:
    //   0: aload_1
    //   1: invokevirtual 150	android/content/Context:getResources	()Landroid/content/res/Resources;
    //   4: invokevirtual 156	android/content/res/Resources:getAssets	()Landroid/content/res/AssetManager;
    //   7: astore_1
    //   8: aload_1
    //   9: aload_0
    //   10: invokevirtual 162	android/content/res/AssetManager:open	(Ljava/lang/String;)Ljava/io/InputStream;
    //   13: astore_1
    //   14: aload_1
    //   15: invokestatic 179	android/graphics/BitmapFactory:decodeStream	(Ljava/io/InputStream;)Landroid/graphics/Bitmap;
    //   18: astore_0
    //   19: aload_1
    //   20: invokevirtual 131	java/io/InputStream:close	()V
    //   23: new 181	android/graphics/drawable/BitmapDrawable
    //   26: dup
    //   27: aload_0
    //   28: invokespecial 184	android/graphics/drawable/BitmapDrawable:<init>	(Landroid/graphics/Bitmap;)V
    //   31: areturn
    //   32: astore_1
    //   33: aconst_null
    //   34: astore_0
    //   35: aload_1
    //   36: invokevirtual 128	java/io/IOException:printStackTrace	()V
    //   39: goto -16 -> 23
    //   42: astore_1
    //   43: goto -8 -> 35
    // Local variable table:
    //   start	length	slot	name	signature
    //   0	46	0	paramString	String
    //   0	46	1	paramContext	Context
    // Exception table:
    //   from	to	target	type
    //   8	19	32	java/io/IOException
    //   19	23	42	java/io/IOException
  }
  
  /* Error */
  public static void outLog2SD(String paramString, boolean paramBoolean)
  {
    // Byte code:
    //   0: aconst_null
    //   1: astore_3
    //   2: aconst_null
    //   3: astore 4
    //   5: new 12	java/lang/StringBuilder
    //   8: dup
    //   9: invokespecial 13	java/lang/StringBuilder:<init>	()V
    //   12: invokestatic 19	android/os/Environment:getExternalStorageDirectory	()Ljava/io/File;
    //   15: invokevirtual 25	java/io/File:getAbsolutePath	()Ljava/lang/String;
    //   18: invokevirtual 29	java/lang/StringBuilder:append	(Ljava/lang/String;)Ljava/lang/StringBuilder;
    //   21: ldc -68
    //   23: invokevirtual 29	java/lang/StringBuilder:append	(Ljava/lang/String;)Ljava/lang/StringBuilder;
    //   26: invokevirtual 34	java/lang/StringBuilder:toString	()Ljava/lang/String;
    //   29: astore 5
    //   31: aload_3
    //   32: astore_2
    //   33: new 21	java/io/File
    //   36: dup
    //   37: aload 5
    //   39: invokespecial 41	java/io/File:<init>	(Ljava/lang/String;)V
    //   42: astore 5
    //   44: aload_3
    //   45: astore_2
    //   46: aload 5
    //   48: invokevirtual 45	java/io/File:exists	()Z
    //   51: ifeq +11 -> 62
    //   54: aload_3
    //   55: astore_2
    //   56: aload 5
    //   58: invokevirtual 191	java/io/File:createNewFile	()Z
    //   61: pop
    //   62: aload_3
    //   63: astore_2
    //   64: new 193	java/io/FileWriter
    //   67: dup
    //   68: aload 5
    //   70: iload_1
    //   71: invokespecial 196	java/io/FileWriter:<init>	(Ljava/io/File;Z)V
    //   74: astore_3
    //   75: aload_3
    //   76: ldc -58
    //   78: invokevirtual 200	java/io/FileWriter:write	(Ljava/lang/String;)V
    //   81: aload_3
    //   82: aload_0
    //   83: invokevirtual 203	java/io/FileWriter:append	(Ljava/lang/CharSequence;)Ljava/io/Writer;
    //   86: pop
    //   87: aload_3
    //   88: invokevirtual 204	java/io/FileWriter:flush	()V
    //   91: aload_3
    //   92: invokevirtual 205	java/io/FileWriter:close	()V
    //   95: return
    //   96: astore_0
    //   97: aload_0
    //   98: invokevirtual 128	java/io/IOException:printStackTrace	()V
    //   101: return
    //   102: astore_3
    //   103: aload 4
    //   105: astore_0
    //   106: aload_0
    //   107: astore_2
    //   108: aload_3
    //   109: invokevirtual 133	java/lang/Exception:printStackTrace	()V
    //   112: aload_0
    //   113: invokevirtual 205	java/io/FileWriter:close	()V
    //   116: return
    //   117: astore_0
    //   118: aload_0
    //   119: invokevirtual 128	java/io/IOException:printStackTrace	()V
    //   122: return
    //   123: astore_0
    //   124: aload_2
    //   125: invokevirtual 205	java/io/FileWriter:close	()V
    //   128: aload_0
    //   129: athrow
    //   130: astore_2
    //   131: aload_2
    //   132: invokevirtual 128	java/io/IOException:printStackTrace	()V
    //   135: goto -7 -> 128
    //   138: astore_0
    //   139: aload_3
    //   140: astore_2
    //   141: goto -17 -> 124
    //   144: astore_2
    //   145: aload_3
    //   146: astore_0
    //   147: aload_2
    //   148: astore_3
    //   149: goto -43 -> 106
    // Local variable table:
    //   start	length	slot	name	signature
    //   0	152	0	paramString	String
    //   0	152	1	paramBoolean	boolean
    //   32	93	2	localObject1	Object
    //   130	2	2	localIOException	java.io.IOException
    //   140	1	2	localException1	Exception
    //   144	4	2	localException2	Exception
    //   1	91	3	localFileWriter	java.io.FileWriter
    //   102	44	3	localException3	Exception
    //   148	1	3	localObject2	Object
    //   3	101	4	localObject3	Object
    //   29	40	5	localObject4	Object
    // Exception table:
    //   from	to	target	type
    //   91	95	96	java/io/IOException
    //   33	44	102	java/lang/Exception
    //   46	54	102	java/lang/Exception
    //   56	62	102	java/lang/Exception
    //   64	75	102	java/lang/Exception
    //   112	116	117	java/io/IOException
    //   33	44	123	finally
    //   46	54	123	finally
    //   56	62	123	finally
    //   64	75	123	finally
    //   108	112	123	finally
    //   124	128	130	java/io/IOException
    //   75	91	138	finally
    //   75	91	144	java/lang/Exception
  }
  
  public static String readFileSD(File paramFile)
  {
    String str2 = null;
    if (!paramFile.exists())
    {
      System.out.println("文件不存在：" + paramFile);
      return null;
    }
    String str1 = str2;
    try
    {
      FileInputStream localFileInputStream = new FileInputStream(paramFile);
      str1 = str2;
      byte[] arrayOfByte = new byte[localFileInputStream.available()];
      str1 = str2;
      localFileInputStream.read(arrayOfByte);
      str1 = str2;
      str2 = EncodingUtils.getString(arrayOfByte, "UTF-8");
      str1 = str2;
      localFileInputStream.close();
      return str2;
    }
    catch (Exception localException)
    {
      localException.printStackTrace();
      System.out.println("文件读取失败" + paramFile);
    }
    return str1;
  }
  
  public static String readFileSD(String paramString)
  {
    String str = null;
    File localFile = new File(paramString);
    if (!localFile.exists())
    {
      System.out.println("文件不存在：" + localFile);
      return null;
    }
    paramString = str;
    try
    {
      FileInputStream localFileInputStream = new FileInputStream(localFile);
      paramString = str;
      byte[] arrayOfByte = new byte[localFileInputStream.available()];
      paramString = str;
      localFileInputStream.read(arrayOfByte);
      paramString = str;
      str = EncodingUtils.getString(arrayOfByte, "UTF-8");
      paramString = str;
      localFileInputStream.close();
      return str;
    }
    catch (Exception localException)
    {
      localException.printStackTrace();
      System.out.println("文件读取失败" + localFile);
    }
    return paramString;
  }
  
  /* Error */
  public static java.util.ArrayList<String> readLines(String paramString)
  {
    // Byte code:
    //   0: new 248	java/util/ArrayList
    //   3: dup
    //   4: invokespecial 249	java/util/ArrayList:<init>	()V
    //   7: astore_2
    //   8: new 142	java/io/BufferedReader
    //   11: dup
    //   12: new 144	java/io/InputStreamReader
    //   15: dup
    //   16: new 226	java/io/FileInputStream
    //   19: dup
    //   20: aload_0
    //   21: invokespecial 250	java/io/FileInputStream:<init>	(Ljava/lang/String;)V
    //   24: invokespecial 165	java/io/InputStreamReader:<init>	(Ljava/io/InputStream;)V
    //   27: invokespecial 168	java/io/BufferedReader:<init>	(Ljava/io/Reader;)V
    //   30: astore_1
    //   31: aload_1
    //   32: invokevirtual 171	java/io/BufferedReader:readLine	()Ljava/lang/String;
    //   35: astore_0
    //   36: aload_0
    //   37: ifnull +19 -> 56
    //   40: aload_2
    //   41: aload_0
    //   42: invokevirtual 254	java/util/ArrayList:add	(Ljava/lang/Object;)Z
    //   45: pop
    //   46: goto -15 -> 31
    //   49: astore_0
    //   50: aload_1
    //   51: invokevirtual 255	java/io/BufferedReader:close	()V
    //   54: aload_0
    //   55: athrow
    //   56: aload_1
    //   57: invokevirtual 255	java/io/BufferedReader:close	()V
    //   60: aload_2
    //   61: areturn
    //   62: astore_0
    //   63: aload_2
    //   64: areturn
    //   65: astore_1
    //   66: goto -12 -> 54
    //   69: astore_0
    //   70: aconst_null
    //   71: astore_1
    //   72: goto -22 -> 50
    // Local variable table:
    //   start	length	slot	name	signature
    //   0	75	0	paramString	String
    //   30	27	1	localBufferedReader	BufferedReader
    //   65	1	1	localException	Exception
    //   71	1	1	localObject	Object
    //   7	57	2	localArrayList	java.util.ArrayList
    // Exception table:
    //   from	to	target	type
    //   31	36	49	finally
    //   40	46	49	finally
    //   56	60	62	java/lang/Exception
    //   50	54	65	java/lang/Exception
    //   0	31	69	finally
  }
  
  public File creatSDDir(String paramString)
  {
    return new File(this.SDCardRoot + paramString + File.separator);
  }
  
  public File createFileInSDCard(String paramString1, String paramString2)
  {
    paramString1 = new File(this.SDCardRoot + paramString2 + File.separator + paramString1);
    paramString1.createNewFile();
    return paramString1;
  }
  
  public boolean isFileExist(String paramString1, String paramString2)
  {
    paramString1 = new File(this.SDCardRoot + paramString2 + File.separator + paramString1);
    if (paramString1.exists()) {
      paramString1.delete();
    }
    return paramString1.exists();
  }
  
  /* Error */
  public File write2SDFromInput(String paramString1, String paramString2, java.io.InputStream paramInputStream, android.os.Handler paramHandler)
  {
    // Byte code:
    //   0: iconst_0
    //   1: istore 5
    //   3: aload_0
    //   4: aload_1
    //   5: invokevirtual 270	cn/apppark/mcd/util/file/SDFileUtils:creatSDDir	(Ljava/lang/String;)Ljava/io/File;
    //   8: pop
    //   9: aload_0
    //   10: aload_2
    //   11: aload_1
    //   12: invokevirtual 272	cn/apppark/mcd/util/file/SDFileUtils:createFileInSDCard	(Ljava/lang/String;Ljava/lang/String;)Ljava/io/File;
    //   15: astore 7
    //   17: new 112	java/io/FileOutputStream
    //   20: dup
    //   21: aload 7
    //   23: invokespecial 115	java/io/FileOutputStream:<init>	(Ljava/io/File;)V
    //   26: astore_1
    //   27: aload_1
    //   28: astore_2
    //   29: sipush 1024
    //   32: newarray <illegal type>
    //   34: astore 8
    //   36: aload_1
    //   37: astore_2
    //   38: aload_3
    //   39: aload 8
    //   41: invokevirtual 121	java/io/InputStream:read	([B)I
    //   44: istore 6
    //   46: iload 6
    //   48: iconst_m1
    //   49: if_icmpeq +76 -> 125
    //   52: aload_1
    //   53: astore_2
    //   54: aload_1
    //   55: aload 8
    //   57: iconst_0
    //   58: iload 6
    //   60: invokevirtual 275	java/io/OutputStream:write	([BII)V
    //   63: iload 5
    //   65: iload 6
    //   67: iadd
    //   68: istore 5
    //   70: aload_1
    //   71: astore_2
    //   72: new 277	android/os/Message
    //   75: dup
    //   76: invokespecial 278	android/os/Message:<init>	()V
    //   79: astore 9
    //   81: aload_1
    //   82: astore_2
    //   83: aload 9
    //   85: iconst_m1
    //   86: putfield 282	android/os/Message:what	I
    //   89: aload_1
    //   90: astore_2
    //   91: aload 9
    //   93: iload 5
    //   95: putfield 285	android/os/Message:arg1	I
    //   98: aload_1
    //   99: astore_2
    //   100: aload 4
    //   102: aload 9
    //   104: invokevirtual 291	android/os/Handler:sendMessage	(Landroid/os/Message;)Z
    //   107: pop
    //   108: goto -72 -> 36
    //   111: astore_3
    //   112: aload_1
    //   113: astore_2
    //   114: aload_3
    //   115: invokevirtual 133	java/lang/Exception:printStackTrace	()V
    //   118: aload_1
    //   119: invokevirtual 292	java/io/OutputStream:close	()V
    //   122: aload 7
    //   124: areturn
    //   125: aload_1
    //   126: astore_2
    //   127: aload_1
    //   128: invokevirtual 293	java/io/OutputStream:flush	()V
    //   131: aload_1
    //   132: invokevirtual 292	java/io/OutputStream:close	()V
    //   135: aload 7
    //   137: areturn
    //   138: astore_1
    //   139: aload_1
    //   140: invokevirtual 133	java/lang/Exception:printStackTrace	()V
    //   143: aload 7
    //   145: areturn
    //   146: astore_1
    //   147: aload_1
    //   148: invokevirtual 133	java/lang/Exception:printStackTrace	()V
    //   151: aload 7
    //   153: areturn
    //   154: astore_1
    //   155: aconst_null
    //   156: astore_2
    //   157: aload_2
    //   158: invokevirtual 292	java/io/OutputStream:close	()V
    //   161: aload_1
    //   162: athrow
    //   163: astore_2
    //   164: aload_2
    //   165: invokevirtual 133	java/lang/Exception:printStackTrace	()V
    //   168: goto -7 -> 161
    //   171: astore_1
    //   172: goto -15 -> 157
    //   175: astore_3
    //   176: aconst_null
    //   177: astore_1
    //   178: aconst_null
    //   179: astore 7
    //   181: goto -69 -> 112
    //   184: astore_3
    //   185: aconst_null
    //   186: astore_1
    //   187: goto -75 -> 112
    // Local variable table:
    //   start	length	slot	name	signature
    //   0	190	0	this	SDFileUtils
    //   0	190	1	paramString1	String
    //   0	190	2	paramString2	String
    //   0	190	3	paramInputStream	java.io.InputStream
    //   0	190	4	paramHandler	android.os.Handler
    //   1	93	5	i	int
    //   44	24	6	j	int
    //   15	165	7	localFile	File
    //   34	22	8	arrayOfByte	byte[]
    //   79	24	9	localMessage	android.os.Message
    // Exception table:
    //   from	to	target	type
    //   29	36	111	java/lang/Exception
    //   38	46	111	java/lang/Exception
    //   54	63	111	java/lang/Exception
    //   72	81	111	java/lang/Exception
    //   83	89	111	java/lang/Exception
    //   91	98	111	java/lang/Exception
    //   100	108	111	java/lang/Exception
    //   127	131	111	java/lang/Exception
    //   131	135	138	java/lang/Exception
    //   118	122	146	java/lang/Exception
    //   3	17	154	finally
    //   17	27	154	finally
    //   157	161	163	java/lang/Exception
    //   29	36	171	finally
    //   38	46	171	finally
    //   54	63	171	finally
    //   72	81	171	finally
    //   83	89	171	finally
    //   91	98	171	finally
    //   100	108	171	finally
    //   114	118	171	finally
    //   127	131	171	finally
    //   3	17	175	java/lang/Exception
    //   17	27	184	java/lang/Exception
  }
}


/* Location:              /Users/makito/Apktool/sunshine_app.apk/classes-dex2jar.jar!/cn/apppark/mcd/util/file/SDFileUtils.class
 * Java compiler version: 6 (50.0)
 * JD-Core Version:       0.7.1
 */