import cn.apppark.vertify.activity.free.dyn.DynRss5003;

public final class jp
  implements Runnable
{
  public jp(DynRss5003 paramDynRss5003, int paramInt) {}
  
  /* Error */
  public final void run()
  {
    // Byte code:
    //   0: iconst_1
    //   1: istore_3
    //   2: iconst_0
    //   3: istore_2
    //   4: new 25	org/mozilla/intl/chardet/nsDetector
    //   7: dup
    //   8: iconst_0
    //   9: invokespecial 28	org/mozilla/intl/chardet/nsDetector:<init>	(I)V
    //   12: astore 5
    //   14: aload 5
    //   16: new 30	jq
    //   19: dup
    //   20: aload_0
    //   21: invokespecial 33	jq:<init>	(Ljp;)V
    //   24: invokevirtual 37	org/mozilla/intl/chardet/nsDetector:Init	(Lorg/mozilla/intl/chardet/nsICharsetDetectionObserver;)V
    //   27: new 39	java/net/URL
    //   30: dup
    //   31: aload_0
    //   32: getfield 14	jp:b	Lcn/apppark/vertify/activity/free/dyn/DynRss5003;
    //   35: invokestatic 45	cn/apppark/vertify/activity/free/dyn/DynRss5003:g	(Lcn/apppark/vertify/activity/free/dyn/DynRss5003;)Lcn/apppark/mcd/vo/dyn/DynRss5003Vo;
    //   38: invokevirtual 51	cn/apppark/mcd/vo/dyn/DynRss5003Vo:getInterfaces	()Ljava/lang/String;
    //   41: invokespecial 54	java/net/URL:<init>	(Ljava/lang/String;)V
    //   44: astore 6
    //   46: new 56	java/io/BufferedInputStream
    //   49: dup
    //   50: aload 6
    //   52: invokevirtual 60	java/net/URL:openStream	()Ljava/io/InputStream;
    //   55: invokespecial 63	java/io/BufferedInputStream:<init>	(Ljava/io/InputStream;)V
    //   58: astore 7
    //   60: sipush 1024
    //   63: newarray <illegal type>
    //   65: astore 8
    //   67: aload 7
    //   69: aload 8
    //   71: iconst_0
    //   72: aload 8
    //   74: arraylength
    //   75: invokevirtual 67	java/io/BufferedInputStream:read	([BII)I
    //   78: istore_1
    //   79: iload_1
    //   80: iconst_m1
    //   81: if_icmpeq +51 -> 132
    //   84: iload_3
    //   85: istore 4
    //   87: iload_3
    //   88: ifeq +13 -> 101
    //   91: aload 5
    //   93: aload 8
    //   95: iload_1
    //   96: invokevirtual 71	org/mozilla/intl/chardet/nsDetector:isAscii	([BI)Z
    //   99: istore 4
    //   101: iload 4
    //   103: istore_3
    //   104: iload 4
    //   106: ifne -39 -> 67
    //   109: iload 4
    //   111: istore_3
    //   112: iload_2
    //   113: ifne -46 -> 67
    //   116: aload 5
    //   118: aload 8
    //   120: iload_1
    //   121: iconst_0
    //   122: invokevirtual 75	org/mozilla/intl/chardet/nsDetector:DoIt	([BIZ)Z
    //   125: istore_2
    //   126: iload 4
    //   128: istore_3
    //   129: goto -62 -> 67
    //   132: aload 5
    //   134: invokevirtual 78	org/mozilla/intl/chardet/nsDetector:DataEnd	()V
    //   137: iload_3
    //   138: ifeq +12 -> 150
    //   141: aload_0
    //   142: getfield 14	jp:b	Lcn/apppark/vertify/activity/free/dyn/DynRss5003;
    //   145: iconst_1
    //   146: invokestatic 81	cn/apppark/vertify/activity/free/dyn/DynRss5003:a	(Lcn/apppark/vertify/activity/free/dyn/DynRss5003;Z)Z
    //   149: pop
    //   150: aload_0
    //   151: getfield 14	jp:b	Lcn/apppark/vertify/activity/free/dyn/DynRss5003;
    //   154: invokestatic 85	cn/apppark/vertify/activity/free/dyn/DynRss5003:h	(Lcn/apppark/vertify/activity/free/dyn/DynRss5003;)Z
    //   157: ifne +90 -> 247
    //   160: aload_0
    //   161: getfield 14	jp:b	Lcn/apppark/vertify/activity/free/dyn/DynRss5003;
    //   164: aload_0
    //   165: getfield 14	jp:b	Lcn/apppark/vertify/activity/free/dyn/DynRss5003;
    //   168: invokestatic 45	cn/apppark/vertify/activity/free/dyn/DynRss5003:g	(Lcn/apppark/vertify/activity/free/dyn/DynRss5003;)Lcn/apppark/mcd/vo/dyn/DynRss5003Vo;
    //   171: invokevirtual 88	cn/apppark/mcd/vo/dyn/DynRss5003Vo:getStyle_codeType	()Ljava/lang/String;
    //   174: invokestatic 91	cn/apppark/vertify/activity/free/dyn/DynRss5003:a	(Lcn/apppark/vertify/activity/free/dyn/DynRss5003;Ljava/lang/String;)Ljava/lang/String;
    //   177: pop
    //   178: aload_0
    //   179: getfield 14	jp:b	Lcn/apppark/vertify/activity/free/dyn/DynRss5003;
    //   182: getstatic 97	cn/apppark/vertify/network/request/WebServiceRequest:NO_DATA	Ljava/lang/String;
    //   185: invokestatic 99	cn/apppark/vertify/activity/free/dyn/DynRss5003:b	(Lcn/apppark/vertify/activity/free/dyn/DynRss5003;Ljava/lang/String;)Ljava/lang/String;
    //   188: pop
    //   189: invokestatic 105	android/os/Message:obtain	()Landroid/os/Message;
    //   192: astore 5
    //   194: aload 5
    //   196: aload_0
    //   197: getfield 16	jp:a	I
    //   200: putfield 108	android/os/Message:what	I
    //   203: new 110	android/os/Bundle
    //   206: dup
    //   207: invokespecial 111	android/os/Bundle:<init>	()V
    //   210: astore 6
    //   212: aload 6
    //   214: ldc 113
    //   216: aload_0
    //   217: getfield 14	jp:b	Lcn/apppark/vertify/activity/free/dyn/DynRss5003;
    //   220: invokestatic 117	cn/apppark/vertify/activity/free/dyn/DynRss5003:i	(Lcn/apppark/vertify/activity/free/dyn/DynRss5003;)Ljava/lang/String;
    //   223: invokevirtual 121	android/os/Bundle:putString	(Ljava/lang/String;Ljava/lang/String;)V
    //   226: aload 5
    //   228: aload 6
    //   230: invokevirtual 125	android/os/Message:setData	(Landroid/os/Bundle;)V
    //   233: aload_0
    //   234: getfield 14	jp:b	Lcn/apppark/vertify/activity/free/dyn/DynRss5003;
    //   237: invokestatic 129	cn/apppark/vertify/activity/free/dyn/DynRss5003:j	(Lcn/apppark/vertify/activity/free/dyn/DynRss5003;)Ljr;
    //   240: aload 5
    //   242: invokevirtual 135	jr:sendMessage	(Landroid/os/Message;)Z
    //   245: pop
    //   246: return
    //   247: aload 6
    //   249: invokevirtual 139	java/net/URL:openConnection	()Ljava/net/URLConnection;
    //   252: checkcast 141	java/net/HttpURLConnection
    //   255: astore 5
    //   257: aload 5
    //   259: ldc -114
    //   261: invokevirtual 145	java/net/HttpURLConnection:setReadTimeout	(I)V
    //   264: aload 5
    //   266: ldc -109
    //   268: ldc -107
    //   270: invokevirtual 152	java/net/HttpURLConnection:setRequestProperty	(Ljava/lang/String;Ljava/lang/String;)V
    //   273: aload 5
    //   275: ldc -102
    //   277: invokevirtual 157	java/net/HttpURLConnection:setRequestMethod	(Ljava/lang/String;)V
    //   280: aload 5
    //   282: invokevirtual 161	java/net/HttpURLConnection:getResponseCode	()I
    //   285: sipush 200
    //   288: if_icmpne -99 -> 189
    //   291: aload_0
    //   292: getfield 14	jp:b	Lcn/apppark/vertify/activity/free/dyn/DynRss5003;
    //   295: aload 5
    //   297: invokevirtual 164	java/net/HttpURLConnection:getInputStream	()Ljava/io/InputStream;
    //   300: invokevirtual 167	cn/apppark/vertify/activity/free/dyn/DynRss5003:read	(Ljava/io/InputStream;)[B
    //   303: astore 5
    //   305: aload_0
    //   306: getfield 14	jp:b	Lcn/apppark/vertify/activity/free/dyn/DynRss5003;
    //   309: new 169	java/lang/String
    //   312: dup
    //   313: aload 5
    //   315: aload_0
    //   316: getfield 14	jp:b	Lcn/apppark/vertify/activity/free/dyn/DynRss5003;
    //   319: invokestatic 172	cn/apppark/vertify/activity/free/dyn/DynRss5003:c	(Lcn/apppark/vertify/activity/free/dyn/DynRss5003;)Ljava/lang/String;
    //   322: invokespecial 175	java/lang/String:<init>	([BLjava/lang/String;)V
    //   325: invokestatic 99	cn/apppark/vertify/activity/free/dyn/DynRss5003:b	(Lcn/apppark/vertify/activity/free/dyn/DynRss5003;Ljava/lang/String;)Ljava/lang/String;
    //   328: pop
    //   329: goto -140 -> 189
    //   332: astore 5
    //   334: aload_0
    //   335: getfield 14	jp:b	Lcn/apppark/vertify/activity/free/dyn/DynRss5003;
    //   338: getstatic 178	cn/apppark/vertify/network/request/WebServiceRequest:WEB_ERROR	Ljava/lang/String;
    //   341: invokestatic 99	cn/apppark/vertify/activity/free/dyn/DynRss5003:b	(Lcn/apppark/vertify/activity/free/dyn/DynRss5003;Ljava/lang/String;)Ljava/lang/String;
    //   344: pop
    //   345: aload 5
    //   347: invokevirtual 181	java/lang/Exception:printStackTrace	()V
    //   350: invokestatic 105	android/os/Message:obtain	()Landroid/os/Message;
    //   353: astore 5
    //   355: aload 5
    //   357: aload_0
    //   358: getfield 16	jp:a	I
    //   361: putfield 108	android/os/Message:what	I
    //   364: new 110	android/os/Bundle
    //   367: dup
    //   368: invokespecial 111	android/os/Bundle:<init>	()V
    //   371: astore 6
    //   373: aload 6
    //   375: ldc 113
    //   377: aload_0
    //   378: getfield 14	jp:b	Lcn/apppark/vertify/activity/free/dyn/DynRss5003;
    //   381: invokestatic 117	cn/apppark/vertify/activity/free/dyn/DynRss5003:i	(Lcn/apppark/vertify/activity/free/dyn/DynRss5003;)Ljava/lang/String;
    //   384: invokevirtual 121	android/os/Bundle:putString	(Ljava/lang/String;Ljava/lang/String;)V
    //   387: aload 5
    //   389: aload 6
    //   391: invokevirtual 125	android/os/Message:setData	(Landroid/os/Bundle;)V
    //   394: aload_0
    //   395: getfield 14	jp:b	Lcn/apppark/vertify/activity/free/dyn/DynRss5003;
    //   398: invokestatic 129	cn/apppark/vertify/activity/free/dyn/DynRss5003:j	(Lcn/apppark/vertify/activity/free/dyn/DynRss5003;)Ljr;
    //   401: aload 5
    //   403: invokevirtual 135	jr:sendMessage	(Landroid/os/Message;)Z
    //   406: pop
    //   407: return
    //   408: astore 5
    //   410: invokestatic 105	android/os/Message:obtain	()Landroid/os/Message;
    //   413: astore 6
    //   415: aload 6
    //   417: aload_0
    //   418: getfield 16	jp:a	I
    //   421: putfield 108	android/os/Message:what	I
    //   424: new 110	android/os/Bundle
    //   427: dup
    //   428: invokespecial 111	android/os/Bundle:<init>	()V
    //   431: astore 7
    //   433: aload 7
    //   435: ldc 113
    //   437: aload_0
    //   438: getfield 14	jp:b	Lcn/apppark/vertify/activity/free/dyn/DynRss5003;
    //   441: invokestatic 117	cn/apppark/vertify/activity/free/dyn/DynRss5003:i	(Lcn/apppark/vertify/activity/free/dyn/DynRss5003;)Ljava/lang/String;
    //   444: invokevirtual 121	android/os/Bundle:putString	(Ljava/lang/String;Ljava/lang/String;)V
    //   447: aload 6
    //   449: aload 7
    //   451: invokevirtual 125	android/os/Message:setData	(Landroid/os/Bundle;)V
    //   454: aload_0
    //   455: getfield 14	jp:b	Lcn/apppark/vertify/activity/free/dyn/DynRss5003;
    //   458: invokestatic 129	cn/apppark/vertify/activity/free/dyn/DynRss5003:j	(Lcn/apppark/vertify/activity/free/dyn/DynRss5003;)Ljr;
    //   461: aload 6
    //   463: invokevirtual 135	jr:sendMessage	(Landroid/os/Message;)Z
    //   466: pop
    //   467: aload 5
    //   469: athrow
    // Local variable table:
    //   start	length	slot	name	signature
    //   0	470	0	this	jp
    //   78	43	1	i	int
    //   3	123	2	bool1	boolean
    //   1	137	3	bool2	boolean
    //   85	42	4	bool3	boolean
    //   12	302	5	localObject1	Object
    //   332	14	5	localException	Exception
    //   353	49	5	localMessage	android.os.Message
    //   408	60	5	localObject2	Object
    //   44	418	6	localObject3	Object
    //   58	392	7	localObject4	Object
    //   65	54	8	arrayOfByte	byte[]
    // Exception table:
    //   from	to	target	type
    //   4	67	332	java/lang/Exception
    //   67	79	332	java/lang/Exception
    //   91	101	332	java/lang/Exception
    //   116	126	332	java/lang/Exception
    //   132	137	332	java/lang/Exception
    //   141	150	332	java/lang/Exception
    //   150	189	332	java/lang/Exception
    //   247	329	332	java/lang/Exception
    //   4	67	408	finally
    //   67	79	408	finally
    //   91	101	408	finally
    //   116	126	408	finally
    //   132	137	408	finally
    //   141	150	408	finally
    //   150	189	408	finally
    //   247	329	408	finally
    //   334	350	408	finally
  }
}


/* Location:              /Users/makito/Apktool/sunshine_app.apk/classes-dex2jar.jar!/jp.class
 * Java compiler version: 6 (50.0)
 * JD-Core Version:       0.7.1
 */