package com.tencent.stat;

class t
  implements Runnable
{
  t(n paramn) {}
  
  /* Error */
  public void run()
  {
    // Byte code:
    //   0: aload_0
    //   1: getfield 12	com/tencent/stat/t:a	Lcom/tencent/stat/n;
    //   4: invokestatic 25	com/tencent/stat/n:b	(Lcom/tencent/stat/n;)Lcom/tencent/stat/w;
    //   7: invokevirtual 31	com/tencent/stat/w:getReadableDatabase	()Landroid/database/sqlite/SQLiteDatabase;
    //   10: ldc 33
    //   12: aconst_null
    //   13: aconst_null
    //   14: aconst_null
    //   15: aconst_null
    //   16: aconst_null
    //   17: aconst_null
    //   18: invokevirtual 39	android/database/sqlite/SQLiteDatabase:query	(Ljava/lang/String;[Ljava/lang/String;Ljava/lang/String;[Ljava/lang/String;Ljava/lang/String;Ljava/lang/String;Ljava/lang/String;)Landroid/database/Cursor;
    //   21: astore 4
    //   23: aload 4
    //   25: astore_3
    //   26: aload 4
    //   28: invokeinterface 45 1 0
    //   33: ifeq +148 -> 181
    //   36: aload 4
    //   38: astore_3
    //   39: aload 4
    //   41: iconst_0
    //   42: invokeinterface 49 2 0
    //   47: istore_1
    //   48: aload 4
    //   50: astore_3
    //   51: aload 4
    //   53: iconst_1
    //   54: invokeinterface 53 2 0
    //   59: astore 5
    //   61: aload 4
    //   63: astore_3
    //   64: aload 4
    //   66: iconst_2
    //   67: invokeinterface 53 2 0
    //   72: astore 6
    //   74: aload 4
    //   76: astore_3
    //   77: aload 4
    //   79: iconst_3
    //   80: invokeinterface 49 2 0
    //   85: istore_2
    //   86: aload 4
    //   88: astore_3
    //   89: new 55	com/tencent/stat/b
    //   92: dup
    //   93: iload_1
    //   94: invokespecial 58	com/tencent/stat/b:<init>	(I)V
    //   97: astore 7
    //   99: aload 4
    //   101: astore_3
    //   102: aload 7
    //   104: iload_1
    //   105: putfield 61	com/tencent/stat/b:a	I
    //   108: aload 4
    //   110: astore_3
    //   111: aload 7
    //   113: new 63	org/json/JSONObject
    //   116: dup
    //   117: aload 5
    //   119: invokespecial 66	org/json/JSONObject:<init>	(Ljava/lang/String;)V
    //   122: putfield 69	com/tencent/stat/b:b	Lorg/json/JSONObject;
    //   125: aload 4
    //   127: astore_3
    //   128: aload 7
    //   130: aload 6
    //   132: putfield 73	com/tencent/stat/b:c	Ljava/lang/String;
    //   135: aload 4
    //   137: astore_3
    //   138: aload 7
    //   140: iload_2
    //   141: putfield 76	com/tencent/stat/b:d	I
    //   144: aload 4
    //   146: astore_3
    //   147: aload 7
    //   149: invokestatic 81	com/tencent/stat/StatConfig:a	(Lcom/tencent/stat/b;)V
    //   152: goto -129 -> 23
    //   155: astore 5
    //   157: aload 4
    //   159: astore_3
    //   160: invokestatic 84	com/tencent/stat/n:d	()Lcom/tencent/stat/common/StatLogger;
    //   163: aload 5
    //   165: invokevirtual 90	com/tencent/stat/common/StatLogger:e	(Ljava/lang/Object;)V
    //   168: aload 4
    //   170: ifnull +10 -> 180
    //   173: aload 4
    //   175: invokeinterface 93 1 0
    //   180: return
    //   181: aload 4
    //   183: ifnull -3 -> 180
    //   186: aload 4
    //   188: invokeinterface 93 1 0
    //   193: return
    //   194: astore 4
    //   196: aconst_null
    //   197: astore_3
    //   198: aload_3
    //   199: ifnull +9 -> 208
    //   202: aload_3
    //   203: invokeinterface 93 1 0
    //   208: aload 4
    //   210: athrow
    //   211: astore 4
    //   213: goto -15 -> 198
    //   216: astore 5
    //   218: aconst_null
    //   219: astore 4
    //   221: goto -64 -> 157
    // Local variable table:
    //   start	length	slot	name	signature
    //   0	224	0	this	t
    //   47	58	1	i	int
    //   85	56	2	j	int
    //   25	178	3	localCursor1	android.database.Cursor
    //   21	166	4	localCursor2	android.database.Cursor
    //   194	15	4	localObject1	Object
    //   211	1	4	localObject2	Object
    //   219	1	4	localObject3	Object
    //   59	59	5	str1	String
    //   155	9	5	localThrowable1	Throwable
    //   216	1	5	localThrowable2	Throwable
    //   72	59	6	str2	String
    //   97	51	7	localb	b
    // Exception table:
    //   from	to	target	type
    //   26	36	155	java/lang/Throwable
    //   39	48	155	java/lang/Throwable
    //   51	61	155	java/lang/Throwable
    //   64	74	155	java/lang/Throwable
    //   77	86	155	java/lang/Throwable
    //   89	99	155	java/lang/Throwable
    //   102	108	155	java/lang/Throwable
    //   111	125	155	java/lang/Throwable
    //   128	135	155	java/lang/Throwable
    //   138	144	155	java/lang/Throwable
    //   147	152	155	java/lang/Throwable
    //   0	23	194	finally
    //   26	36	211	finally
    //   39	48	211	finally
    //   51	61	211	finally
    //   64	74	211	finally
    //   77	86	211	finally
    //   89	99	211	finally
    //   102	108	211	finally
    //   111	125	211	finally
    //   128	135	211	finally
    //   138	144	211	finally
    //   147	152	211	finally
    //   160	168	211	finally
    //   0	23	216	java/lang/Throwable
  }
}


/* Location:              /Users/makito/Apktool/sunshine_app.apk/classes-dex2jar.jar!/com/tencent/stat/t.class
 * Java compiler version: 6 (50.0)
 * JD-Core Version:       0.7.1
 */